mylib_044/__init__.py
mylib_044-0.1.dist-info/LICENSE.txt
mylib_044-0.1.dist-info/METADATA
mylib_044-0.1.dist-info/WHEEL
mylib_044-0.1.dist-info/top_level.txt
mylib_044-0.1.dist-info/RECORD
